solace/README.md
solace/__init__.py
solace/config.ini
solace/licenses.txt
solace/version.txt
solace/messaging/__init__.py
solace/messaging/_messaging_service_utility.py
solace/messaging/message.py
solace/messaging/messaging_service.py
solace/messaging/_impl/__init__.py
solace/messaging/_impl/_interoperability_support.py
solace/messaging/_impl/_transactional_error_subcodes.py
solace/messaging/_solace_logging/__init__.py
solace/messaging/_solace_logging/_core_api_log.py
solace/messaging/builder/__init__.py
solace/messaging/builder/direct_message_publisher_builder.py
solace/messaging/builder/direct_message_receiver_builder.py
solace/messaging/builder/message_publisher_builder.py
solace/messaging/builder/message_receiver_builder.py
solace/messaging/builder/persistent_message_publisher_builder.py
solace/messaging/builder/persistent_message_receiver_builder.py
solace/messaging/builder/request_reply_message_publisher_builder.py
solace/messaging/builder/request_reply_message_receiver_builder.py
solace/messaging/builder/transactional_message_publisher_builder.py
solace/messaging/builder/transactional_message_receiver_builder.py
solace/messaging/builder/_impl/__init__.py
solace/messaging/builder/_impl/_direct_message_publisher_builder.py
solace/messaging/builder/_impl/_direct_message_receiver_builder.py
solace/messaging/builder/_impl/_message_publisher_builder.py
solace/messaging/builder/_impl/_message_receiver_builder.py
solace/messaging/builder/_impl/_message_replay_config.py
solace/messaging/builder/_impl/_persistent_message_publisher_builder.py
solace/messaging/builder/_impl/_persistent_message_receiver_builder.py
solace/messaging/builder/_impl/_request_reply_message_publisher_builder.py
solace/messaging/builder/_impl/_request_reply_message_receiver_builder.py
solace/messaging/builder/_impl/_transactional_message_publisher_builder.py
solace/messaging/builder/_impl/_transactional_message_receiver_builder.py
solace/messaging/config/__init__.py
solace_pubsubplus-1.9.0.dist-info/LICENSE.txt
solace_pubsubplus-1.9.0.dist-info/METADATA
solace_pubsubplus-1.9.0.dist-info/NOTICE.txt
solace_pubsubplus-1.9.0.dist-info/WHEEL
solace_pubsubplus-1.9.0.dist-info/top_level.txt
solace_pubsubplus-1.9.0.dist-info/RECORD
