Metadata-Version: 2.1
Name: solace-pubsubplus
Version: 1.9.0
Summary: Solace PubSub+ Messaging API for Python.
Home-page: https://docs.solace.com/Solace-PubSub-Messaging-APIs/Python-API/python-home.htm
Author: Solace Corporation
Author-email: info@solace.com
License: Apache 2.0
Classifier: Programming Language :: Python :: 3.6
Classifier: Programming Language :: Python :: 3.7
Classifier: Programming Language :: Python :: 3.8
Classifier: Programming Language :: Python :: 3.9
Classifier: Programming Language :: Python :: 3.10
Classifier: Development Status :: 5 - Production/Stable
Classifier: Operating System :: Microsoft :: Windows :: Windows 10
Classifier: Operating System :: POSIX :: Linux
Classifier: Operating System :: MacOS :: MacOS X
Classifier: Intended Audience :: Developers
Classifier: Topic :: Software Development :: Libraries :: Application Frameworks
Classifier: Topic :: Software Development :: Libraries :: Python Modules
Classifier: License :: OSI Approved :: Apache Software License
Requires-Python: >=3.6
License-File: LICENSE.txt
License-File: NOTICE.txt
